gftools/__init__.py
gftools/dividend.py
gftools/financials.py
gftools/price.py
gftools/valuation.py
h2w_gftools-1.1.0.dist-info/METADATA
h2w_gftools-1.1.0.dist-info/WHEEL
h2w_gftools-1.1.0.dist-info/top_level.txt
h2w_gftools-1.1.0.dist-info/RECORD
